ONTraC/__init__.py
ONTraC/constants.py
ONTraC/data.py
ONTraC/log.py
ONTraC/version.py
ONTraC/GNN/_GNN.py
ONTraC/GNN/__init__.py
ONTraC/analysis/__init__.py
ONTraC/analysis/cell_type.py
ONTraC/analysis/constants.py
ONTraC/analysis/data.py
ONTraC/analysis/niche_cluster.py
ONTraC/analysis/niche_net.py
ONTraC/analysis/spatial.py
ONTraC/analysis/train_loss.py
ONTraC/analysis/trajectory.py
ONTraC/analysis/utils.py
ONTraC/bin/NicheTrajectory.py
ONTraC/bin/ONTraC.py
ONTraC/bin/ONTraC_GNN.py
ONTraC/bin/ONTraC_GP.py
ONTraC/bin/ONTraC_GT.py
ONTraC/bin/ONTraC_NN.py
ONTraC/bin/ONTraC_NT.py
ONTraC/bin/ONTraC_analysis.py
ONTraC/bin/__init__.py
ONTraC/external/STdeconvolve.R
ONTraC/external/__init__.py
ONTraC/external/deconvolution.py
ONTraC/integrate/__init__.py
ONTraC/integrate/general_control.py
ONTraC/model/__init__.py
ONTraC/model/_model.py
ONTraC/model/dmon_exp_pool.py
ONTraC/model/norm_dense_gcn_conv.py
ONTraC/niche_net/__init__.py
ONTraC/niche_net/_niche_net.py
ONTraC/niche_trajectory/__init__.py
ONTraC/niche_trajectory/_niche_trajectory.py
ONTraC/niche_trajectory/algorithm.py
ONTraC/optparser/_IO.py
ONTraC/optparser/_NN.py
ONTraC/optparser/_NT.py
ONTraC/optparser/__init__.py
ONTraC/optparser/_analysis.py
ONTraC/optparser/_preprocessing.py
ONTraC/optparser/_train.py
ONTraC/optparser/command.py
ONTraC/preprocessing/__inti__.py
ONTraC/preprocessing/data.py
ONTraC/preprocessing/expression.py
ONTraC/preprocessing/pp_control.py
ONTraC/run/__init__.py
ONTraC/run/processes.py
ONTraC/train/__init__.py
ONTraC/train/_batch_train.py
ONTraC/train/inspect_funcs.py
ONTraC/train/loss_funs.py
ONTraC/utils/__init__.py
ONTraC/utils/_utils.py
ONTraC/utils/decorators.py
ontrac-2.0.8.dist-info/licenses/LICENSE
ontrac-2.0.8.dist-info/METADATA
ontrac-2.0.8.dist-info/WHEEL
ontrac-2.0.8.dist-info/entry_points.txt
ontrac-2.0.8.dist-info/top_level.txt
ontrac-2.0.8.dist-info/RECORD
