Metadata-Version: 2.4
Name: ONTraC
Version: 2.0.8
Summary: A niche-centered, machine learning method for constructing spatially continuous trajectories
Author-email: Wen Wang <wwang.bio@gmail.com>, Shiwei Zheng <swzheng29@gmail.com>, Sujung Crystal Shin <sjcshin5040@gmail.com>, "Joselyn C. Chávez-Fuentes" <joselynchavezf@gmail.com>, Guo-Cheng Yuan <gcyuan@gmail.com>
License: MIT
Project-URL: Homepage, https://github.com/gyuanlab/ONTraC
Project-URL: Repository, https://github.com/gyuanlab/ONTraC
Project-URL: Issue Tracker, https://github.com/gyuanlab/ONTraC/issues
Keywords: graph neural network,pytorch,pytorch geometric,trajectory inference,spatial omics
Classifier: Development Status :: 5 - Production/Stable
Classifier: Intended Audience :: Science/Research
Classifier: License :: OSI Approved :: MIT License
Classifier: Operating System :: OS Independent
Classifier: Programming Language :: Python :: 3
Classifier: Programming Language :: Python :: 3.10
Classifier: Programming Language :: Python :: 3.11
Classifier: Programming Language :: Python :: 3.12
Classifier: Topic :: Software Development :: Libraries :: Python Modules
Requires-Python: <3.13,>=3.10
License-File: LICENSE
Requires-Dist: pyyaml==6.0.1
Requires-Dist: pandas==2.2.1
Requires-Dist: scipy<1.15.0a0,>=1.14.0
Requires-Dist: torch<2.8.0a0,>=2.7.1-rc1
Requires-Dist: torch-geometric<2.7.0a0,>=2.6.0
Requires-Dist: umap-learn==0.5.6
Requires-Dist: harmonypy==0.0.10
Requires-Dist: leidenalg==0.10.2
Requires-Dist: session-info
Provides-Extra: analysis
Requires-Dist: matplotlib<3.9; extra == "analysis"
Requires-Dist: seaborn; extra == "analysis"
Provides-Extra: test
Requires-Dist: matplotlib<3.9; extra == "test"
Requires-Dist: seaborn; extra == "test"
Requires-Dist: pytest; extra == "test"
Requires-Dist: black; extra == "test"
Requires-Dist: flake8; extra == "test"
Requires-Dist: isort; extra == "test"
Requires-Dist: mypy; extra == "test"
Provides-Extra: dev
Requires-Dist: matplotlib<3.9; extra == "dev"
Requires-Dist: seaborn; extra == "dev"
Requires-Dist: pytest; extra == "dev"
Requires-Dist: black; extra == "dev"
Requires-Dist: flake8; extra == "dev"
Requires-Dist: isort; extra == "dev"
Requires-Dist: mypy; extra == "dev"
Requires-Dist: pre-commit; extra == "dev"
Requires-Dist: setuptools; extra == "dev"
Requires-Dist: twine; extra == "dev"
Requires-Dist: build; extra == "dev"
Dynamic: license-file
